{
  "animals": [
    {
      "id": 1,
      "name": "Doodles",
      "breed": "Poodle"
    },
    {
      "id": 3,
      "name": "Esme",
      "breed": "Pitbull"
    },
    {
      "name": "Taco",
      "breed": "Bulldog",
      "id": 4
    },
    {
      "name": "Thomas",
      "breed": "Staffordshire Terrier",
      "id": 5
    },
    {
      "name": "Sammie",
      "breed": "Lab Mix",
      "id": 6
    },
    {
      "name": "Coco",
      "breed": "crazydog",
      "id": 8
    },
    {
      "name": "macy",
      "breed": "lab mix",
      "id": 9
    }
  ],
  "locations": [
    {
      "id": 1,
      "name": "Nashville North",
      "city": "Nashville"
    },
    {
      "id": 2,
      "name": "Nashville South",
      "city": "Nashville"
    },
    {
      "id": 3,
      "name": "Nashville East",
      "city": "Nashville"
    }
  ],
  "employees": [
    {
      "id": 1,
      "name": "Susie Smith"
    },
    {
      "id": 2,
      "name": "Tom Thompson"
    },
    {
      "id": 3,
      "name": "Earl Erlhander"
    },
    {
      "name": "Steve Mostly",
      "id": 4
    },
    {
      "name": "Steve Justice 2",
      "id": 5
    },
    {
      "name": "Thomas Crutcher",
      "id": 6
    },
    {
      "name": "Thomas Banks",
      "id": 7
    },
    {
      "name": "Sandy Woods",
      "id": 8
    },
    {
      "name": "Sandy Hooker",
      "id": 9
    },
    {
      "name": "Tommy Core",
      "id": 10
    },
    {
      "name": "Tommy D",
      "id": 11
    },
    {
      "name": "Tommy E",
      "id": 12
    },
    {
      "name": "Coco Dogmatic",
      "id": 13
    },
    {
      "name": "Tommy Burns",
      "id": 15
    }
  ],
  "owners": [
    {
      "id": 1,
      "name": "Owen Owner",
      "phoneNumber": "615-333-4444"
    },
    {
      "id": 2,
      "name": "Sue Owner",
      "phoneNumber": "423-222-3333"
    },
    {
      "id": 3,
      "name": "Bob Owner",
      "phoneNumber": "222-444-5555"
    }
  ]
}